[{"line":1,"elements":[{"start_timestamp":"2025-07-28T14:32:57.206Z","line":4,"name":"User creates a new blog post successfully","description":"","id":"creating--editing--and-deleting-blog-posts-(uı-tests);user-creates-a-new-blog-post-successfully","after":[{"result":{"duration":1529400,"status":"passed"},"match":{"location":"com.remwaste.step_definitions.Hooks.tearDown(io.cucumber.java.Scenario)"}}],"type":"scenario","keyword":"Scenario","steps":[{"result":{"duration":4327630500,"status":"passed"},"line":6,"name":"the user is logged in to the platform","match":{"location":"com.remwaste.step_definitions.UiSteps.the_user_is_logged_in_to_the_platform()"},"keyword":"Given "},{"result":{"duration":47246200,"status":"passed"},"line":7,"name":"the user clicks on the user icon at the top right corner","match":{"location":"com.remwaste.step_definitions.LoginSteps.the_user_clicks_on_the_user_icon_at_the_top_right_corner()"},"keyword":"When "},{"result":{"duration":928974200,"status":"passed"},"line":8,"name":"the user selects the New option from the dropdown","match":{"location":"com.remwaste.step_definitions.UiSteps.the_user_selects_the_new_option_from_the_dropdown()"},"keyword":"And "},{"result":{"duration":7648300,"status":"passed"},"line":9,"name":"the user is redirected to the new blog page in the same tab","match":{"location":"com.remwaste.step_definitions.UiSteps.the_user_is_redirected_to_the_new_blog_page_in_the_same_tab()"},"keyword":"And "},{"result":{"duration":156444400,"status":"passed"},"line":10,"name":"the user enters a title into the title input box","match":{"location":"com.remwaste.step_definitions.UiSteps.the_user_enters_a_title_into_the_title_input_box()"},"keyword":"And "},{"result":{"duration":41081900,"status":"passed"},"line":11,"name":"the user enters an image url into the image url input box","match":{"location":"com.remwaste.step_definitions.UiSteps.the_user_enters_an_image_url_into_the_image_url_input_box()"},"keyword":"And "},{"result":{"duration":40565100,"status":"passed"},"line":12,"name":"the user enters blog details into the detail input box","match":{"location":"com.remwaste.step_definitions.UiSteps.the_user_enters_blog_details_into_the_detail_input_box()"},"keyword":"And "},{"result":{"duration":114662300,"status":"passed"},"line":13,"name":"the user clicks on the add new blog button","match":{"location":"com.remwaste.step_definitions.UiSteps.the_user_clicks_on_the_add_new_blog_button()"},"keyword":"And "},{"result":{"duration":57975200,"status":"passed"},"line":14,"name":"the new blog post should appear on the blog dashboard","match":{"location":"com.remwaste.step_definitions.UiSteps.the_new_blog_post_should_appear_on_the_blog_dashboard()"},"keyword":"Then "}],"tags":[{"name":"@scenario_6"}]}],"name":"Creating, editing, and deleting blog posts (UI Tests)","description":"","id":"creating--editing--and-deleting-blog-posts-(uı-tests)","keyword":"Feature","uri":"file:src/test/resources/ui.feature","tags":[]}]